README.rst
setup.py
commondata.eg.egg-info/PKG-INFO
commondata.eg.egg-info/SOURCES.txt
commondata.eg.egg-info/dependency_links.txt
commondata.eg.egg-info/namespace_packages.txt
commondata.eg.egg-info/requires.txt
commondata.eg.egg-info/top_level.txt
commondata/eg/__init__.py
commondata/eg/alexandria.py
commondata/eg/cairo.py
commondata/eg/damietta.py
commondata/eg/giza.py
commondata/eg/places.py
commondata/eg/port_said.py