Metadata-Version: 1.1
Name: commondata.eg
Version: 0.0.3
Summary: Common data about Egypt
Home-page: https://github.com/ExcellentServ/commondata-eg
Author: Mahmoud Mamdouh
Author-email: sharedup@gmail.com
License: BSD license
Platform: UNKNOWN
Classifier: Programming Language :: Python
Classifier: Programming Language :: Python :: 2.6
Classifier: Programming Language :: Python :: 2.7
Classifier: Development Status :: 4 - Beta
Classifier: Intended Audience :: Developers
Classifier: License :: OSI Approved :: BSD License
Classifier: Natural Language :: English
Classifier: Natural Language :: Arabic
Classifier: Operating System :: OS Independent
